[1,["7dj5uJT9FMn6OrOOx83tfK@f9941","20g1ukYUVPvKWKBRznAKo+@6c48a","0bGVCrTAtBXozaW+4r2LjN","c1VwBRDndKS7PHjVeoIQ72@f9941","20g1ukYUVPvKWKBRznAKo+@f9941","54TknWPwVPqJqeCR+Y/Czo@f9941","95EkngnxZFbYuFpsqVTaFr@f9941","67ymYnS9REpq9e5LcOimLO@f9941","80iRiXH91Izp6t7X/OtqVT@f9941","de9p8ISXdE+JSFk1RhXNNJ@f9941","54TknWPwVPqJqeCR+Y/Czo@6c48a","67ymYnS9REpq9e5LcOimLO@6c48a","7dj5uJT9FMn6OrOOx83tfK@6c48a","80iRiXH91Izp6t7X/OtqVT@6c48a","95EkngnxZFbYuFpsqVTaFr@6c48a","c1VwBRDndKS7PHjVeoIQ72@6c48a","de9p8ISXdE+JSFk1RhXNNJ@6c48a"],["node","_textureSource","_spriteFrame","_cameraComponent","btnBack","stonesNode","boardNode","moveCountLabel","timerLabel","statusLabel","_target","scene","_parent","_clip","_normalSprite","_hoverSprite","_pressedSprite","_disabledSprite","boardSpriteFrame","blackStoneSF","whiteStoneSF"],["cc.SpriteFrame",["cc.Node",["_name","_layer","_id","_objFlags","_components","_parent","_children","_lpos"],-1,9,1,2,5],["cc.Label",["_string","_actualFontSize","_fontSize","_isBold","_overflow","_enableWrapText","node","_color"],-3,1,5],["cc.Node",["_name","_layer","_parent","_components","_lpos"],1,1,12,5],["cc.UITransform",["node","_contentSize"],3,1,5],["cc.Sprite",["_sizeMode","node","_spriteFrame","_color"],2,1,6,5],["cc.AudioClip",["_name","_native","_duration"],0],["cc.SceneAsset",["_name"],2],["cc.Node",["_name","_parent","_components","_lpos"],2,1,2,5],["cc.Canvas",["node","_cameraComponent"],3,1,1],["cc.Widget",["_alignFlags","_top","_bottom","node"],0,1],["479b1+Ek0FMvoAPH3PTfwa7",["node","statusLabel","timerLabel","moveCountLabel","boardNode","stonesNode","btnBack","boardSpriteFrame","blackStoneSF","whiteStoneSF"],3,1,1,1,1,1,1,1,6,6,6],["cc.Button",["_transition","node","_normalColor","_target","_normalSprite","_hoverSprite","_pressedSprite","_disabledSprite"],2,1,5,1,6,6,6,6],["cc.AudioSource",["_volume","node","_clip"],2,1,6],["cc.Graphics",["node"],3,1],["cc.Scene",["_name","_children","_globals"],2,2,4],["cc.SceneGlobals",["ambient","shadows","_skybox","fog","octree","skin","lightProbeInfo","postSettings"],3,4,4,4,4,4,4,4,4],["cc.AmbientInfo",["_skyColorHDR","_groundAlbedoHDR"],3,5,5],["cc.ShadowsInfo",["_shadowColor","_size"],3,5,5],["cc.SkyboxInfo",[],3],["cc.FogInfo",[],3],["cc.OctreeInfo",[],3],["cc.SkinInfo",["_enabled"],2],["cc.LightProbeInfo",[],3],["cc.PostSettingsInfo",[],3],["cc.Camera",["_projection","_orthoHeight","_near","_visibility","node","_color"],-1,1,5]],[[4,0,1,1],[1,0,1,5,4,3],[1,0,1,5,6,4,7,3],[3,0,1,2,3,4,3],[4,0,1],[5,0,1,3,2,2],[2,0,1,2,3,6,7,5],[6,0,1,2,4],[7,0,2],[1,0,1,2,6,4,7,4],[1,0,3,1,5,4,4],[3,0,1,2,3,3],[8,0,1,2,3,2],[9,0,1,1],[10,0,1,2,3,4],[11,0,1,2,3,4,5,6,7,8,9,1],[5,0,1,2,2],[12,0,1,2,3,4,5,6,7,2],[13,0,1,2,2],[14,0,1],[2,0,1,2,4,5,3,6,7,7],[2,0,1,2,6,7,4],[15,0,1,2,2],[16,0,1,2,3,4,5,6,7,1],[17,0,1,1],[18,0,1,1],[19,1],[20,1],[21,1],[22,0,2],[23,1],[24,1],[25,0,1,2,3,4,5,5]],[[[[7,"inilagu",".mp3",189.23102],-1],0,0,[],[],[]],[[{"name":"default_btn_normal","rect":{"x":0,"y":0,"width":40,"height":40},"offset":{"x":0,"y":0},"originalSize":{"width":40,"height":40},"rotated":false,"capInsets":[12,12,12,12],"vertices":{"rawPosition":[-20,-20,0,20,-20,0,-20,20,0,20,20,0],"indexes":[0,1,2,2,1,3],"uv":[0,40,40,40,0,0,40,0],"nuv":[0,0,1,0,0,1,1,1],"minPos":{"x":-20,"y":-20,"z":0},"maxPos":{"x":20,"y":20,"z":0}},"packable":true,"pixelsToUnit":100,"pivot":{"x":0.5,"y":0.5},"meshType":0}],[0],0,[0],[1],[1]],[[[8,"GameScene2"],[9,"Canvas",33554432,"beI88Z2HpFELqR4T5EMHpg",[-12,-13,-14,-15,-16,-17],[[0,-1,[5,1280,720]],[13,-3,-2],[14,45,5.684341886080802e-14,5.684341886080802e-14,-4],[15,-11,-10,-9,-8,-7,-6,-5,8,9,10]],[1,640,360.00000000000006,0]],[2,"BackButton",33554432,1,[-22],[[0,-18,[5,100,40]],[5,0,-19,[4,4286802022],3],[17,2,-21,[4,4292269782],-20,4,5,6,7]],[1,-500,305,0]],[2,"BoardContainer",33554432,1,[-24,-25,-26],[[0,-23,[5,540,540]]],[1,0,-20,0]],[2,"StatusBar",33554432,1,[-28,-29,-30],[[0,-27,[5,1280,60]]],[1,0,305,0]],[1,"bgm",33554432,1,[[4,-31],[18,0.001,-32,0]]],[1,"Background",33554432,1,[[0,-33,[5,1280,720]],[5,0,-34,[4,4281212446],1]]],[3,"StatusText",33554432,4,[[[0,-35,[5,101.8359375,50.4]],-36],4,1],[1,-350,0,0]],[11,"Timer",33554432,4,[[[0,-37,[5,56.267578125,50.4]],-38],4,1]],[3,"MoveCount",33554432,4,[[[0,-39,[5,73.0283203125,50.4]],-40],4,1],[1,350,0,0]],[1,"BoardBG",33554432,3,[[0,-41,[5,540,540]],[16,0,-42,2]]],[1,"Grid",33554432,3,[[4,-43],[19,-44]]],[1,"Stones",33554432,3,[[0,-45,[5,540,540]]]],[10,"Label",512,33554432,2,[[0,-46,[5,100,40]],[20,"Back",16,16,1,false,true,-47,[4,4294235853]]]],[22,"GameScene2",[1],[23,[24,[2,0,0,0,0.520833125],[2,0,0,0,0]],[25,[4,4283190348],[0,512,512]],[26],[27],[28],[29,false],[30],[31]]],[12,"Camera",1,[-48],[1,0,0,1000]],[32,0,360,0,1108344832,15,[4,4278190080]],[6,"Your Turn",22,22,true,7,[4,4285769419]],[6,"00:00",22,22,true,8,[4,4294235853]],[21,"Moves: 0",18,18,9,[4,4291341734]]],0,[0,0,1,0,3,16,0,0,1,0,0,1,0,4,2,0,5,12,0,6,3,0,7,19,0,8,18,0,9,17,0,0,1,0,-1,5,0,-2,15,0,-3,6,0,-4,4,0,-5,3,0,-6,2,0,0,2,0,0,2,0,10,2,0,0,2,0,-1,13,0,0,3,0,-1,10,0,-2,11,0,-3,12,0,0,4,0,-1,7,0,-2,8,0,-3,9,0,0,5,0,0,5,0,0,6,0,0,6,0,0,7,0,-2,17,0,0,8,0,-2,18,0,0,9,0,-2,19,0,0,10,0,0,10,0,0,11,0,0,11,0,0,12,0,0,13,0,0,13,0,-1,16,0,11,14,1,12,14,48],[0,0,0,0,0,0,0,0,0,0,0],[13,2,2,2,14,15,16,17,18,19,20],[2,0,3,0,0,4,5,6,7,8,9]],[[{"name":"default_btn_pressed","rect":{"x":0,"y":0,"width":40,"height":40},"offset":{"x":0,"y":0},"originalSize":{"width":40,"height":40},"rotated":false,"capInsets":[12,12,12,12],"vertices":{"rawPosition":[-20,-20,0,20,-20,0,-20,20,0,20,20,0],"indexes":[0,1,2,2,1,3],"uv":[0,40,40,40,0,0,40,0],"nuv":[0,0,1,0,0,1,1,1],"minPos":{"x":-20,"y":-20,"z":0},"maxPos":{"x":20,"y":20,"z":0}},"packable":true,"pixelsToUnit":100,"pivot":{"x":0.5,"y":0.5},"meshType":0}],[0],0,[0],[1],[10]],[[{"name":"boardnew","rect":{"x":0,"y":0,"width":1254,"height":1254},"offset":{"x":0,"y":0},"originalSize":{"width":1254,"height":1254},"rotated":false,"capInsets":[0,0,0,0],"vertices":{"rawPosition":[-627,-627,0,627,-627,0,-627,627,0,627,627,0],"indexes":[0,1,2,2,1,3],"uv":[0,1254,1254,1254,0,0,1254,0],"nuv":[0,0,1,0,0,1,1,1],"minPos":{"x":-627,"y":-627,"z":0},"maxPos":{"x":627,"y":627,"z":0}},"packable":true,"pixelsToUnit":100,"pivot":{"x":0.5,"y":0.5},"meshType":0}],[0],0,[0],[1],[11]],[[{"name":"default_sprite_splash","rect":{"x":0,"y":0,"width":2,"height":2},"offset":{"x":0,"y":0},"originalSize":{"width":2,"height":2},"rotated":false,"capInsets":[0,0,0,0],"vertices":{"rawPosition":[-1,-1,0,1,-1,0,-1,1,0,1,1,0],"indexes":[0,1,2,2,1,3],"uv":[0,2,2,2,0,0,2,0],"nuv":[0,0,1,0,0,1,1,1],"minPos":{"x":-1,"y":-1,"z":0},"maxPos":{"x":1,"y":1,"z":0}},"packable":true,"pixelsToUnit":100,"pivot":{"x":0.5,"y":0.5},"meshType":0}],[0],0,[0],[1],[12]],[[{"name":"stone_black","rect":{"x":2,"y":2,"width":600,"height":600},"offset":{"x":0,"y":0},"originalSize":{"width":604,"height":604},"rotated":false,"capInsets":[0,0,0,0],"vertices":{"rawPosition":[-300,-300,0,300,-300,0,-300,300,0,300,300,0],"indexes":[0,1,2,2,1,3],"uv":[2,602,602,602,2,2,602,2],"nuv":[0.0033112582781456954,0.0033112582781456954,0.9966887417218543,0.0033112582781456954,0.0033112582781456954,0.9966887417218543,0.9966887417218543,0.9966887417218543],"minPos":{"x":-300,"y":-300,"z":0},"maxPos":{"x":300,"y":300,"z":0}},"packable":true,"pixelsToUnit":100,"pivot":{"x":0.5,"y":0.5},"meshType":0}],[0],0,[0],[1],[13]],[[{"name":"default_btn_disabled","rect":{"x":0,"y":0,"width":40,"height":40},"offset":{"x":0,"y":0},"originalSize":{"width":40,"height":40},"rotated":false,"capInsets":[12,12,12,12],"vertices":{"rawPosition":[-20,-20,0,20,-20,0,-20,20,0,20,20,0],"indexes":[0,1,2,2,1,3],"uv":[0,40,40,40,0,0,40,0],"nuv":[0,0,1,0,0,1,1,1],"minPos":{"x":-20,"y":-20,"z":0},"maxPos":{"x":20,"y":20,"z":0}},"packable":true,"pixelsToUnit":100,"pivot":{"x":0.5,"y":0.5},"meshType":0}],[0],0,[0],[1],[14]],[[{"name":"baseboard","rect":{"x":0,"y":0,"width":441,"height":441},"offset":{"x":0,"y":0},"originalSize":{"width":441,"height":441},"rotated":false,"capInsets":[0,0,0,0],"vertices":{"rawPosition":[-220.5,-220.5,0,220.5,-220.5,0,-220.5,220.5,0,220.5,220.5,0],"indexes":[0,1,2,2,1,3],"uv":[0,441,441,441,0,0,441,0],"nuv":[0,0,1,0,0,1,1,1],"minPos":{"x":-220.5,"y":-220.5,"z":0},"maxPos":{"x":220.5,"y":220.5,"z":0}},"packable":true,"pixelsToUnit":100,"pivot":{"x":0.5,"y":0.5},"meshType":0}],[0],0,[0],[1],[15]],[[{"name":"stone_white","rect":{"x":0,"y":0,"width":1024,"height":1024},"offset":{"x":0,"y":0},"originalSize":{"width":1024,"height":1024},"rotated":false,"capInsets":[0,0,0,0],"vertices":{"rawPosition":[-512,-512,0,512,-512,0,-512,512,0,512,512,0],"indexes":[0,1,2,2,1,3],"uv":[0,1024,1024,1024,0,0,1024,0],"nuv":[0,0,1,0,0,1,1,1],"minPos":{"x":-512,"y":-512,"z":0},"maxPos":{"x":512,"y":512,"z":0}},"packable":true,"pixelsToUnit":100,"pivot":{"x":0.5,"y":0.5},"meshType":0}],[0],0,[0],[1],[16]]]]
